sqlalchemy_acl/__init__.py
sqlalchemy_acl/exceptions.py
sqlalchemy_acl_matt_kubica-0.0.1.dist-info/LICENSE
sqlalchemy_acl_matt_kubica-0.0.1.dist-info/METADATA
sqlalchemy_acl_matt_kubica-0.0.1.dist-info/WHEEL
sqlalchemy_acl_matt_kubica-0.0.1.dist-info/top_level.txt
sqlalchemy_acl_matt_kubica-0.0.1.dist-info/RECORD
