Metadata-Version: 2.1
Name: sqlalchemy-acl-matt-kubica
Version: 0.0.1
Summary: Acces List library for SQLAlchemy ORM
Home-page: https://github.com/matt-kubica/sqlalchemy-acl
Author: Mateusz Kubica
Author-email: mateusz.kubica99@gmail.com
License: UNKNOWN
Platform: UNKNOWN
Classifier: Programming Language :: Python :: 3
Classifier: License :: OSI Approved :: MIT License
Classifier: Operating System :: OS Independent
Requires-Python: >=3.8.6
